[
    {
        "id":105,
        "categoryid":"1002",
        "product_name":"Note 11 pro",
        "img_url":"https://s2.loli.net/2022/01/01/YGcFJgZqjHE5S1p.png",
        "price":"1699"
    },
    {
        "id":106,
        "categoryid":"1002",
        "product_name":"Note 11 4G",
        "img_url":"https://s2.loli.net/2022/01/01/4dJjCzZexIuHcEP.png",
        "price":"1099"
    },
    {
        "id":107,
        "categoryid":"1002",
        "product_name":"Note 11 5G",
        "img_url":"https://s2.loli.net/2022/01/01/cKkgtNpPUhMWy4Q.png",
        "price":"1299"
    },
    {
        "id":108,
        "categoryid":"1002",
        "product_name":"Redmi K40",
        "img_url":"https://s2.loli.net/2022/01/01/yE6JxYBUDSRo8QM.png",
        "price":"2299"
    },
    {
        "id":116,
        "categoryid":"1002",
        "product_name":"K40 游戏增强版",
        "img_url":"https://s2.loli.net/2022/01/03/9RkiBZYywSoOEeC.png",
        "price":"2299"
    },
    {
        "id":117,
        "categoryid":"1002",
        "product_name":"K40 Pro 系列",
        "img_url":"https://s2.loli.net/2022/01/03/mFoPRlIap2MnzdZ.png",
        "price":"2799"
    },
    {
        "id":118,
        "categoryid":"1002",
        "product_name":"Note 10 5G",
        "img_url":"https://s2.loli.net/2022/01/03/utnfFSOBVZ7zQWE.png",
        "price":"1099"
    },
    {
        "id":119,
        "categoryid":"1002",
        "product_name":"Note 10 Pro",
        "img_url":"https://s2.loli.net/2022/01/03/7aryLXIDFlwC1Bm.png",
        "price":"1499"
    },
    {
        "id":120,
        "categoryid":"1002",
        "product_name":"Redmi 9A",
        "img_url":"https://s2.loli.net/2022/01/03/5WsizcEFdVkPohS.jpg",
        "price":"599"
    },
    {
        "id":122,
        "categoryid":"1002",
        "product_name":"黑鲨4S Pro",
        "img_url":"https://s2.loli.net/2022/01/03/O5ZQnqo4pdKysF3.png",
        "price":"5299"
    },
    {
        "id":123,
        "categoryid":"1002",
        "product_name":"黑鲨4S",
        "img_url":"https://s2.loli.net/2022/01/03/yUmXKDVvCGwWcZr.png",
        "price":"2699"
    },
    {
        "id":124,
        "categoryid":"1002",
        "product_name":"Redmi Note 9 4G",
        "img_url":"https://s2.loli.net/2022/01/03/Fj41usEorqPeHJA.png",
        "price":"899"
    }
]